cricket_cli/__init__.py
cricket_cli/cli.py
cricket_cli/cricket_cli.py
cricket_pycli-0.1.0a2.dist-info/LICENSE
cricket_pycli-0.1.0a2.dist-info/METADATA
cricket_pycli-0.1.0a2.dist-info/WHEEL
cricket_pycli-0.1.0a2.dist-info/entry_points.txt
cricket_pycli-0.1.0a2.dist-info/top_level.txt
cricket_pycli-0.1.0a2.dist-info/RECORD
