Metadata-Version: 2.1
Name: cricket-pycli
Version: 0.1.0a2
Summary: 🏏 A CLI for Cricket lovers to get Live Scores, ICC Rankings, Upcoming Matches 🏏
Home-page: https://github.com/kaxil/cricket_cli
Author: Kaxil Naik
License: Apache Software License 2.0
Keywords: cricket_pycli,cricket
Platform: UNKNOWN
Classifier: Development Status :: 2 - Pre-Alpha
Classifier: Intended Audience :: Developers
Classifier: License :: OSI Approved :: Apache Software License
Classifier: Natural Language :: English
Classifier: Programming Language :: Python :: 3
Classifier: Programming Language :: Python :: 3.6
Classifier: Programming Language :: Python :: 3.7
Classifier: Programming Language :: Python :: 3.8
Requires-Python: >=3.6
Requires-Dist: Click (>=7.0)
